pyrealb/Constituent.py
pyrealb/ConstituentEn.py
pyrealb/ConstituentFr.py
pyrealb/Dependent.py
pyrealb/DependentEn.py
pyrealb/DependentFr.py
pyrealb/Lexicon.py
pyrealb/NonTerminalEn.py
pyrealb/NonTerminalFr.py
pyrealb/Number.py
pyrealb/Phrase.py
pyrealb/PhraseEn.py
pyrealb/PhraseFr.py
pyrealb/Terminal.py
pyrealb/TerminalEn.py
pyrealb/TerminalFr.py
pyrealb/__init__.py
pyrealb/lemmatize.py
pyrealb/utils.py
pyrealb/data/LICENSE.txt
pyrealb/data/lexicon-en.json
pyrealb/data/lexicon-en.jsonrnc
pyrealb/data/lexicon-en.jsonrnc.json
pyrealb/data/lexicon-fr.json
pyrealb/data/lexicon-fr.jsonrnc
pyrealb/data/lexicon-fr.jsonrnc.json
pyrealb/data/rules-en.json
pyrealb/data/rules-fr.json
pyrealb/data/pyrealb.egg-info/PKG-INFO
pyrealb/data/pyrealb.egg-info/SOURCES.txt
pyrealb/data/pyrealb.egg-info/dependency_links.txt
pyrealb/data/pyrealb.egg-info/top_level.txt
pyrealb-3.2.dist-info/LICENSE
pyrealb-3.2.dist-info/METADATA
pyrealb-3.2.dist-info/WHEEL
pyrealb-3.2.dist-info/top_level.txt
pyrealb-3.2.dist-info/RECORD
