Metadata-Version: 2.1
Name: pyrealb
Version: 3.2
Summary: A French-English text realizer
Home-page: https://github.com/lapalme/pyrealb
Author: Guy Lapalme
Author-email: lapalme@iro.umontreal.ca
Project-URL: Bug Tracker, https://github.com/lapalme/pyrealb/issues
Classifier: Programming Language :: Python :: 3
Classifier: License :: OSI Approved :: MIT License
Classifier: Operating System :: OS Independent
Requires-Python: >=3.6
License-File: LICENSE
